{
  "unversionedId": "04AddOns/Headwear/MarkIV",
  "id": "04AddOns/Headwear/MarkIV",
  "isDocsHomePage": false,
  "title": "Ultracortex Mark IV",
  "description": "Development Period: January 2016 Through the Present",
  "source": "@site/docs/04AddOns/01-Headwear/01-Ultracortex-Mark-IV.md",
  "sourceDirName": "04AddOns/01-Headwear",
  "slug": "/04AddOns/Headwear/MarkIV",
  "permalink": "/docs/04AddOns/Headwear/MarkIV",
  "editUrl": "https://github.com/OpenBCI/Documentation/edit/master/docs/docs/04AddOns/01-Headwear/01-Ultracortex-Mark-IV.md",
  "version": "current",
  "lastUpdatedBy": "Author",
  "lastUpdatedAt": 1539502055,
  "formattedLastUpdatedAt": "10/14/2018",
  "sidebarPosition": 1,
  "frontMatter": {
    "id": "MarkIV",
    "title": "Ultracortex Mark IV"
  },
  "sidebar": "docs",
  "previous": {
    "title": "Add Ons",
    "permalink": "/docs/04AddOns/AddOnLanding"
  },
  "next": {
    "title": "Ultracortex Mark III",
    "permalink": "/docs/04AddOns/Headwear/MarkIII"
  }
}